setbitcounter/__init__.py
setbitcounter/countset.py
setbitcounter_pkg-1.0.dist-info/LICENCE
setbitcounter_pkg-1.0.dist-info/METADATA
setbitcounter_pkg-1.0.dist-info/WHEEL
setbitcounter_pkg-1.0.dist-info/top_level.txt
setbitcounter_pkg-1.0.dist-info/RECORD
