Metadata-Version: 2.1
Name: setbitcounter-pkg
Version: 1.0
Summary: A package to count set bits of continous natural numbers in a  range
Home-page: https://github.com/diksha-rawat/SetBitCount
Author: Diksha Rawat
Author-email: diksharawat1410@gmail.com
License: UNKNOWN
Platform: UNKNOWN
Classifier: Programming Language :: Python :: 3
Classifier: License :: OSI Approved :: MIT License
Classifier: Operating System :: OS Independent
